appcenter_sdk/__init__.py
appcenter_sdk/api_client.py
appcenter_sdk/configuration.py
appcenter_sdk/rest.py
appcenter_sdk/api/__init__.py
appcenter_sdk/api/account_api.py
appcenter_sdk/api/alerting_api.py
appcenter_sdk/api/analytics_api.py
appcenter_sdk/api/billing_api.py
appcenter_sdk/api/build_api.py
appcenter_sdk/api/codepush_api.py
appcenter_sdk/api/crash_api.py
appcenter_sdk/api/distribute_api.py
appcenter_sdk/api/errors_api.py
appcenter_sdk/api/export_api.py
appcenter_sdk/api/gdpr_api.py
appcenter_sdk/api/mbaas_api.py
appcenter_sdk/api/push_api.py
appcenter_sdk/api/test_api.py
appcenter_sdk/models/AADGroup.py
appcenter_sdk/models/AADTenantAddRequest.py
appcenter_sdk/models/AADTenantResponse.py
appcenter_sdk/models/AADUser.py
appcenter_sdk/models/AccountResponse.py
appcenter_sdk/models/AcquisitionStatusSuccessResponse.py
appcenter_sdk/models/ActiveCrashingAppDetails.py
appcenter_sdk/models/ActiveDeviceCounts.py
appcenter_sdk/models/AddAppTesterRequest.py
appcenter_sdk/models/AddAppTesterResponse.py
appcenter_sdk/models/AddOrganizationAdminRequest.py
appcenter_sdk/models/AddUserAsRoleRequest.py
appcenter_sdk/models/AgentQueueResponse.py
appcenter_sdk/models/AgentQueuesResponse.py
appcenter_sdk/models/AggregatedBillingInformation.py
appcenter_sdk/models/AlertBugTrackerRepo.py
appcenter_sdk/models/AlertBugTrackerRepoOwner.py
appcenter_sdk/models/AlertBugTrackerReposResult.py
appcenter_sdk/models/AlertCrashGroupStateChange.py
appcenter_sdk/models/AlertEmailSettings.py
appcenter_sdk/models/AlertOperationResult.py
appcenter_sdk/models/AlertUserAppEmailSettingsResult.py
appcenter_sdk/models/AlertUserEmailSettingsResult.py
appcenter_sdk/models/AlertWebhook.py
appcenter_sdk/models/AlertWebhookListResult.py
appcenter_sdk/models/AlertWebhookPingResult.py
appcenter_sdk/models/AlertingAccessTokenResponse.py
appcenter_sdk/models/AlertingBugtracker.py
appcenter_sdk/models/AlertingBugtrackerSettings.py
appcenter_sdk/models/AlertingCrashGroup.py
appcenter_sdk-0.0.1.dist-info/LICENSE
appcenter_sdk-0.0.1.dist-info/METADATA
appcenter_sdk-0.0.1.dist-info/WHEEL
appcenter_sdk-0.0.1.dist-info/top_level.txt
appcenter_sdk-0.0.1.dist-info/RECORD
