Metadata-Version: 2.1
Name: appcenter-sdk
Version: 0.0.1
Summary: App Center Client
Home-page: https://github.com/b3nab/appcenter-sdks/sdks/python
Author-email: benedetto.abbenanti@gmail.com
License: UNKNOWN
Keywords: Swagger,App Center Client
Platform: UNKNOWN
Requires-Dist: urllib3 (>=1.15)
Requires-Dist: six (>=1.10)
Requires-Dist: certifi
Requires-Dist: python-dateutil
